[
	{
		"header": {
			"title": "Starter",
			"subtitle": "Free CRM to manage your pipeline.",
			"currency": "$",
			"price": "0",
			"priceLabel": "month",
			"priceMontly": "0",
			"priceLabelMontly": "month",
			"buttonName": "Start Free",
			"buttonLink": "/"
		},
		"body": {
			"listItems": [
				{
					"listItem": "Full CRM — free after trial"
				},
				{
					"listItem": "Contact management"
				},
				{
					"listItem": "Basic analytics"
				},
				{
					"listItem": "1 user"
				}
			]
		},
		"footer": {
			"buttonName": "See all features",
			"buttonLink": "/features"
		},
		"type": "basic"
	},
	{
		"header": {
			"title": "Pro",
			"subtitle": "Power dialer + AI coaching for closers.",
			"currency": "$",
			"price": "20",
			"priceLabel": "month",
			"priceMontly": "20",
			"priceLabelMontly": "month",
			"buttonName": "Start Free Trial",
			"buttonLink": "/"
		},
		"body": {
			"listItems": [
				{
					"listItem": "Everything in Starter"
				},
				{
					"listItem": "Power dialer (multi-line)"
				},
				{
					"listItem": "Local presence"
				},
				{
					"listItem": "Spam shield"
				},
				{
					"listItem": "AI queue management"
				},
				{
					"listItem": "On-call coaching (whispers)"
				},
				{
					"listItem": "Post-call analytics"
				},
				{
					"listItem": "Call transfer"
				},
				{
					"listItem": "Up to 5 users"
				}
			]
		},
		"footer": {
			"buttonName": "See all features",
			"buttonLink": "/features"
		},
		"type": "featured"
	},
	{
		"header": {
			"title": "Team",
			"subtitle": "Scale your sales org with full automation.",
			"currency": "",
			"price": "Custom",
			"priceLabel": "month",
			"priceMontly": "Custom",
			"priceLabelMontly": "month",
			"buttonName": "Contact Sales",
			"buttonLink": "/"
		},
		"body": {
			"listItems": [
				{
					"listItem": "Everything in Pro"
				},
				{
					"listItem": "Lead disbursement"
				},
				{
					"listItem": "Post-sale sequences"
				},
				{
					"listItem": "Pipeline nourishment"
				},
				{
					"listItem": "Chat SDK (Discord, Slack, Teams)"
				},
				{
					"listItem": "Custom integrations"
				},
				{
					"listItem": "Unlimited users"
				}
			]
		},
		"footer": {
			"buttonName": "See all features",
			"buttonLink": "/features"
		},
		"type": "basic"
	}
]
