{
  "query": "how does task:start create a worktree?",
  "budget": 10,
  "results": [
    {
      "path": "packages/workspace/scripts/task-exec.js",
      "score": 1,
      "belief_prior": 0.75,
      "reason": "semantic match: function main",
      "preview": "function main() { const rawArgs = process.argv.slice(2); if (rawArgs.length === 0 || (rawArgs.length === 1 && (rawArgs[0] === '--help' || rawArgs[0] === '-h'))) {",
      "graph_connections": [
        "packages/workspace/scripts/agent.js",
        "packages/workspace/scripts/browser.js",
        "packages/workspace/scripts/check-syntax.js"
      ],
      "graph_connection_count": 3,
      "lines": {
        "start": 31,
        "end": 76
      },
      "score_parts": {
        "boost": 1.6472000000000004,
        "embeddingSimilarity": 0.8032931470113303,
        "changeRelevance": 1,
        "connectedToOtherTopResults": false,
        "graphCentrality": 0.029999999999999995,
        "hasImplementation": true,
        "implementationBonus": 0.05,
        "isTypeHeavy": false,
        "recency": 0.8,
        "nameMatch": 1,
        "rawScore": 1.3231844717570636,
        "weightedEdges": 0.8999999999999999
      }
    },
    {
      "path": "packages/workspace/scripts/lib/task-selection.js",
      "score": 1,
      "belief_prior": 0.6984,
      "reason": "semantic match: function findActiveTaskCandidates",
      "preview": "function findActiveTaskCandidates(repoRoot) { const worktrees = listWorktrees(repoRoot); const tasks = [];",
      "graph_connections": [
        "packages/workspace/scripts/lib/db-guards.js",
        "packages/workspace/scripts/lib/git.js",
        "packages/workspace/scripts/lib/github.js"
      ],
      "graph_connection_count": 3,
      "lines": {
        "start": 96,
        "end": 108
      },
      "score_parts": {
        "boost": 1.3810000000000004,
        "embeddingSimilarity": 0.8483617404310131,
        "changeRelevance": 0.5,
        "connectedToOtherTopResults": false,
        "graphCentrality": 0.029999999999999995,
        "hasImplementation": true,
        "implementationBonus": 0.05,
        "isTypeHeavy": false,
        "recency": 0.8,
        "nameMatch": 1,
        "rawScore": 1.1715875635352295,
        "weightedEdges": 0.8999999999999999
      }
    },
    {
      "path": "packages/workspace/scripts/task-start.js",
      "score": 1,
      "belief_prior": 0.6977,
      "reason": "semantic match: function main part 2",
      "preview": "if (pullRequest.base.ref !== stream) { throw new Error( `pr #${pullRequest.number} targets ${pullRequest.base.ref}, expected ${stream}.\\n` +",
      "graph_connections": [
        "packages/workspace/scripts/agent.js",
        "packages/workspace/scripts/browser.js",
        "packages/workspace/scripts/check-syntax.js"
      ],
      "graph_connection_count": 3,
      "lines": {
        "start": 405,
        "end": 518
      },
      "score_parts": {
        "boost": 1.3810000000000004,
        "embeddingSimilarity": 0.8468755226256768,
        "changeRelevance": 0.5,
        "connectedToOtherTopResults": false,
        "graphCentrality": 0.029999999999999995,
        "hasImplementation": true,
        "implementationBonus": 0.05,
        "isTypeHeavy": false,
        "recency": 0.8,
        "nameMatch": 1,
        "rawScore": 1.16953509674606,
        "weightedEdges": 0.8999999999999999
      }
    },
    {
      "path": "packages/workspace/SCRIPTS.md",
      "score": 1,
      "belief_prior": 0.6918,
      "reason": "semantic match: block task:start — create task branch + worktree + PR",
      "preview": "### task:start — create task branch + worktree + PR creates a new task branch, git worktree, and draft PR. the worktree is created in `/private/tmp/opensaas-worktrees/`. ```bash",
      "graph_connections": [],
      "graph_connection_count": 0,
      "lines": {
        "start": 485,
        "end": 509
      },
      "score_parts": {
        "boost": 1.32,
        "embeddingSimilarity": 0.8728357269187086,
        "changeRelevance": 1,
        "connectedToOtherTopResults": false,
        "graphCentrality": 0,
        "hasImplementation": false,
        "implementationBonus": 0,
        "isTypeHeavy": false,
        "recency": 0.8,
        "nameMatch": 0,
        "rawScore": 1.1521431595326954,
        "weightedEdges": 0
      }
    },
    {
      "path": "packages/workspace/scripts/task-init.js",
      "score": 1,
      "belief_prior": 0.6904,
      "reason": "semantic match: function main",
      "preview": "function main() { const args = parseArgs(process.argv.slice(2)); if (args.help) { printHelp(); return; }",
      "graph_connections": [
        "packages/workspace/scripts/agent.js",
        "packages/workspace/scripts/browser.js",
        "packages/workspace/scripts/check-syntax.js"
      ],
      "graph_connection_count": 3,
      "lines": {
        "start": 71,
        "end": 125
      },
      "score_parts": {
        "boost": 1.3810000000000004,
        "embeddingSimilarity": 0.8311380228651011,
        "changeRelevance": 0.5,
        "connectedToOtherTopResults": false,
        "graphCentrality": 0.029999999999999995,
        "hasImplementation": true,
        "implementationBonus": 0.05,
        "isTypeHeavy": false,
        "recency": 0.8,
        "nameMatch": 1,
        "rawScore": 1.147801609576705,
        "weightedEdges": 0.8999999999999999
      }
    },
    {
      "path": "packages/workspace/scripts/task-push.js",
      "score": 1,
      "belief_prior": 0.6901,
      "reason": "semantic match: function getTaskContext",
      "preview": "function getTaskContext(args) { const startDirectory = path.resolve(args.cwd || process.cwd()); if (hasExplicitTaskSelector(args)) {",
      "graph_connections": [
        "packages/workspace/scripts/agent.js",
        "packages/workspace/scripts/browser.js",
        "packages/workspace/scripts/check-syntax.js"
      ],
      "graph_connection_count": 3,
      "lines": {
        "start": 186,
        "end": 241
      },
      "score_parts": {
        "boost": 1.3810000000000004,
        "embeddingSimilarity": 0.8306019556708071,
        "changeRelevance": 0.5,
        "connectedToOtherTopResults": false,
        "graphCentrality": 0.029999999999999995,
        "hasImplementation": true,
        "implementationBonus": 0.05,
        "isTypeHeavy": false,
        "recency": 0.8,
        "nameMatch": 1,
        "rawScore": 1.147061300781385,
        "weightedEdges": 0.8999999999999999
      }
    },
    {
      "path": "packages/workspace/scripts/task-meta-smoke.js",
      "score": 1,
      "belief_prior": 0.6878,
      "reason": "semantic match: function writeWorkpad",
      "preview": "function writeWorkpad(repoPath, taskBranch, started) { writeFile(path.join(repoPath, '.task', 'workpad.md'), [ `# ${taskBranch}`,",
      "graph_connections": [
        "packages/workspace/scripts/agent.js",
        "packages/workspace/scripts/browser.js",
        "packages/workspace/scripts/check-syntax.js"
      ],
      "graph_connection_count": 3,
      "lines": {
        "start": 39,
        "end": 48
      },
      "score_parts": {
        "boost": 1.3810000000000004,
        "embeddingSimilarity": 0.8256808434362277,
        "changeRelevance": 0.5,
        "connectedToOtherTopResults": false,
        "graphCentrality": 0.029999999999999995,
        "hasImplementation": true,
        "implementationBonus": 0.05,
        "isTypeHeavy": false,
        "recency": 0.8,
        "nameMatch": 1,
        "rawScore": 1.140265244785431,
        "weightedEdges": 0.8999999999999999
      }
    },
    {
      "path": "packages/workspace/scripts/lib/task-meta.js",
      "score": 1,
      "belief_prior": 0.683,
      "reason": "semantic match: function readValidTaskMetaForWorktree",
      "preview": "function readValidTaskMetaForWorktree(worktreePath, branch) { const taskMeta = readTaskMeta(worktreePath); if (!taskMeta) return null;",
      "graph_connections": [
        "packages/workspace/scripts/lib/db-guards.js",
        "packages/workspace/scripts/lib/git.js",
        "packages/workspace/scripts/lib/github.js"
      ],
      "graph_connection_count": 3,
      "lines": {
        "start": 81,
        "end": 86
      },
      "score_parts": {
        "boost": 1.3810000000000004,
        "embeddingSimilarity": 0.8154492425314919,
        "changeRelevance": 0.5,
        "connectedToOtherTopResults": false,
        "graphCentrality": 0.029999999999999995,
        "hasImplementation": true,
        "implementationBonus": 0.05,
        "isTypeHeavy": false,
        "recency": 0.8,
        "nameMatch": 1,
        "rawScore": 1.1261354039359905,
        "weightedEdges": 0.8999999999999999
      }
    },
    {
      "path": "packages/workspace/scripts/task-finish.js",
      "score": 1,
      "belief_prior": 0.6799,
      "reason": "semantic match: function ensureOutsideWorktree",
      "preview": "function ensureOutsideWorktree(repoRoot, worktreePath) { const currentDirectory = path.resolve(process.cwd()); const resolvedWorktreePath = path.resolve(worktreePath);",
      "graph_connections": [
        "packages/workspace/scripts/agent.js",
        "packages/workspace/scripts/browser.js",
        "packages/workspace/scripts/check-syntax.js"
      ],
      "graph_connection_count": 3,
      "lines": {
        "start": 180,
        "end": 190
      },
      "score_parts": {
        "boost": 1.3810000000000004,
        "embeddingSimilarity": 0.8087796080221912,
        "changeRelevance": 0.5,
        "connectedToOtherTopResults": false,
        "graphCentrality": 0.029999999999999995,
        "hasImplementation": true,
        "implementationBonus": 0.05,
        "isTypeHeavy": false,
        "recency": 0.8,
        "nameMatch": 1,
        "rawScore": 1.1169246386786464,
        "weightedEdges": 0.8999999999999999
      }
    },
    {
      "path": "packages/workspace/scripts/lib/git.js",
      "score": 1,
      "belief_prior": 0.6721,
      "reason": "semantic match: function createWorktree",
      "preview": "function createWorktree(repoRoot, worktreePath, branch) { runGit(['worktree', 'add', worktreePath, branch], { cwd: repoRoot }); }",
      "graph_connections": [
        "packages/workspace/scripts/lib/db-guards.js",
        "packages/workspace/scripts/lib/github.js",
        "packages/workspace/scripts/lib/nx-projects.js",
        "packages/workspace/scripts/lib/paths.js",
        "packages/workspace/scripts/lib/task-meta.js",
        "packages/workspace/scripts/lib/task-selection.js",
        "packages/workspace/scripts/lib/validation.js",
        "packages/workspace/scripts/lib/verification.js"
      ],
      "graph_connection_count": 8,
      "lines": {
        "start": 81,
        "end": 83
      },
      "score_parts": {
        "boost": 1.2817800000000004,
        "embeddingSimilarity": 0.8535824762924129,
        "changeRelevance": 0.5,
        "connectedToOtherTopResults": false,
        "graphCentrality": 0.11999999999999997,
        "hasImplementation": true,
        "implementationBonus": 0.05,
        "isTypeHeavy": false,
        "recency": 0.8,
        "nameMatch": 0,
        "rawScore": 1.0941049464620893,
        "weightedEdges": 3.599999999999999
      }
    }
  ],
  "index_stats": {
    "total_files": 14538,
    "total_chunks": 59144,
    "last_indexed": "2026-04-28T16:55:26.269Z",
    "last_full_index": "2026-04-29T01:40:26.658Z",
    "cache_root": "/Users/kokayi/.cache/workspace-index/e8425497c3ee20bf0a28e9da",
    "files_indexed": 0,
    "chunks_embedded": 0
  },
  "belief_version": 2,
  "beliefs": {
    "packages/workspace/scripts/task-exec.js": {
      "prior": 0.75,
      "posterior": 0.8485125000000002,
      "observations": [
        {
          "event_id": "45566724-03f1-4a8e-ae3e-0667be365c88",
          "multiplier": 0.85,
          "reason": "verify failed exploit cluster",
          "type": "verify.fail"
        },
        {
          "event_id": "adc6a418-7fcc-45e3-97fd-d5ec584355ec",
          "multiplier": 1.1,
          "reason": "verify passed exploit cluster",
          "type": "verify.pass"
        },
        {
          "event_id": "0a198141-bf85-4780-bea6-cdb010574355",
          "multiplier": 1.1,
          "reason": "verify passed exploit cluster",
          "type": "verify.pass"
        },
        {
          "event_id": "748bc195-3516-4ee8-8a73-8ac0d892a75c",
          "multiplier": 1.1,
          "reason": "verify passed exploit cluster",
          "type": "verify.pass"
        }
      ]
    },
    "packages/workspace/scripts/lib/task-selection.js": {
      "prior": 0.6984,
      "posterior": 0.6984,
      "observations": []
    },
    "packages/workspace/scripts/task-start.js": {
      "prior": 0.6977,
      "posterior": 0.6977,
      "observations": []
    },
    "packages/workspace/SCRIPTS.md": {
      "prior": 0.6918,
      "posterior": 0.6918,
      "observations": []
    },
    "packages/workspace/scripts/task-init.js": {
      "prior": 0.6904,
      "posterior": 0.6904,
      "observations": []
    },
    "packages/workspace/scripts/task-push.js": {
      "prior": 0.6901,
      "posterior": 0.6901,
      "observations": []
    },
    "packages/workspace/scripts/task-meta-smoke.js": {
      "prior": 0.6878,
      "posterior": 0.6878,
      "observations": []
    },
    "packages/workspace/scripts/lib/task-meta.js": {
      "prior": 0.683,
      "posterior": 0.683,
      "observations": []
    },
    "packages/workspace/scripts/task-finish.js": {
      "prior": 0.6799,
      "posterior": 0.6799,
      "observations": []
    },
    "packages/workspace/scripts/lib/git.js": {
      "prior": 0.6721,
      "posterior": 0.6721,
      "observations": []
    }
  },
  "belief_event_ids": [
    "12c8bdce-07a4-453c-b323-4553aa882024",
    "45566724-03f1-4a8e-ae3e-0667be365c88",
    "adc6a418-7fcc-45e3-97fd-d5ec584355ec",
    "0a198141-bf85-4780-bea6-cdb010574355",
    "ee1d82b3-c9a1-49ca-822e-6415a6d72323",
    "748bc195-3516-4ee8-8a73-8ac0d892a75c"
  ],
  "branch": "task/workspace-agents/workspace-explore-decision-confidence-system",
  "mode": "exploring",
  "worktree_id": "task/workspace-agents/workspace-explore-decision-confidence-system",
  "updated_at": "2026-04-29T04:00:24.507Z",
  "beliefs_updated_at": "2026-04-29T04:00:57.201Z"
}
